yt_dlp_termux_gui/__init__.py
yt_dlp_termux_gui/assets.py
yt_dlp_termux_gui/cli.py
yt_dlp_termux_gui/command.py
yt_dlp_termux_gui/constants.py
yt_dlp_termux_gui/gui.py
yt_dlp_termux_gui/settings.py
yt_dlp_termux_gui/utils.py
yt_dlp_termux_gui/utils_gui.py
yt_dlp_termux_gui/resources/icons/yt-dlp-gui.sh.png
yt_dlp_termux_gui/resources/icons/yt-dlp-gui.sh.svg
yt_dlp_termux_gui/resources/screenshots/gui.png
yt_dlp_termux_gui-1.1.9.dist-info/licenses/LICENSE
yt_dlp_termux_gui-1.1.9.dist-info/METADATA
yt_dlp_termux_gui-1.1.9.dist-info/WHEEL
yt_dlp_termux_gui-1.1.9.dist-info/entry_points.txt
yt_dlp_termux_gui-1.1.9.dist-info/top_level.txt
yt_dlp_termux_gui-1.1.9.dist-info/RECORD
