Metadata-Version: 2.4
Name: yt-dlp-termux-gui
Version: 1.1.9
Summary: Simple yet useful Termux GUI for yt-dlp.
Author: tochi
License: MIT
Project-URL: Homepage, https://github.com/tochiResources/yt-dlp-termux-gui
Project-URL: Source, https://github.com/tochiResources/yt-dlp-termux-gui
Keywords: termux,android,gui,python
Classifier: Programming Language :: Python :: 3
Classifier: Operating System :: Android
Classifier: License :: OSI Approved :: MIT License
Classifier: Intended Audience :: Developers
Requires-Python: >=3.8
License-File: LICENSE
Requires-Dist: termuxgui==0.1.6
Dynamic: license-file
